screenpen/__init__.py
screenpen/__main__.py
screenpen/screenpen.py
screenpen/version.py
screenpen/utils/__init__.py
screenpen/utils/config.ini
screenpen/utils/resources.xml
screenpen/utils/syntax.py
screenpen-0.3.1.dist-info/LICENSE
screenpen-0.3.1.dist-info/LICENSE.txt
screenpen-0.3.1.dist-info/METADATA
screenpen-0.3.1.dist-info/WHEEL
screenpen-0.3.1.dist-info/entry_points.txt
screenpen-0.3.1.dist-info/top_level.txt
screenpen-0.3.1.dist-info/RECORD
