Metadata-Version: 2.1
Name: screenpen
Version: 0.3.1
Summary: Screen annotation software which allows drawing directly on the screen.
Home-page: https://rsusik.github.io/screenpen/
Author: Robert Susik
Author-email: robert.susik@gmail.com
License: GPLv3
Classifier: Environment :: X11 Applications :: Qt
Classifier: Framework :: Matplotlib
Classifier: Intended Audience :: Education
Classifier: Intended Audience :: End Users/Desktop
Classifier: Intended Audience :: Science/Research
Classifier: License :: OSI Approved :: GNU General Public License v3 (GPLv3)
Classifier: Programming Language :: Python
Classifier: Programming Language :: Python :: 3.8
Classifier: Programming Language :: Python :: 3.7
Classifier: Topic :: Communications :: Conferencing
Classifier: Topic :: Education
Classifier: Topic :: Multimedia :: Graphics :: Capture :: Screen Capture
Classifier: Topic :: Multimedia :: Graphics :: Presentation
Requires-Python: >=3.7
License-File: LICENSE
License-File: LICENSE.txt
